biometeo/PET.cpython-38-darwin.so
biometeo/PMV.cpython-38-darwin.so
biometeo/SET.cpython-38-darwin.so
biometeo/Tmrt_utils.cpython-38-darwin.so
biometeo/UTCI.cpython-38-darwin.so
biometeo/__init__.cpython-38-darwin.so
biometeo/mPET.cpython-38-darwin.so
biometeo/utils.cpython-38-darwin.so
biometeo-0.4.0.dist-info/METADATA
biometeo-0.4.0.dist-info/WHEEL
biometeo-0.4.0.dist-info/RECORD
